[
 {
  "alignment": "",
  "allow_in_quick_entry": 0,
  "allow_on_submit": 0,
  "bold": 0,
  "button_color": "",
  "collapsible": 0,
  "collapsible_depends_on": null,
  "columns": 0,
  "default": null,
  "depends_on": null,
  "description": "Quick capture notes from voice/text input",
  "doctype": "Custom Field",
  "dt": "Lead",
  "fetch_from": null,
  "fetch_if_empty": 0,
  "fieldname": "custom_agent_notes",
  "fieldtype": "Small Text",
  "hidden": 0,
  "hide_border": 0,
  "hide_days": 0,
  "hide_seconds": 0,
  "ignore_user_permissions": 0,
  "ignore_xss_filter": 0,
  "in_global_search": 0,
  "in_list_view": 0,
  "in_preview": 0,
  "in_standard_filter": 0,
  "insert_after": "notes",
  "is_system_generated": 0,
  "is_virtual": 0,
  "label": "Agent Notes",
  "length": 0,
  "link_filters": null,
  "mandatory_depends_on": null,
  "module": "Office customisation",
  "name": "Lead-custom_agent_notes",
  "no_copy": 0,
  "non_negative": 0,
  "options": null,
  "permlevel": 0,
  "placeholder": null,
  "precision": "",
  "print_hide": 0,
  "print_hide_if_no_value": 0,
  "print_width": null,
  "read_only": 0,
  "read_only_depends_on": null,
  "report_hide": 0,
  "reqd": 0,
  "search_index": 0,
  "show_dashboard": 0,
  "sort_options": 0,
  "translatable": 0,
  "unique": 0,
  "width": null
 },
 {
  "alignment": "",
  "allow_in_quick_entry": 0,
  "allow_on_submit": 0,
  "bold": 0,
  "button_color": "",
  "collapsible": 0,
  "collapsible_depends_on": null,
  "columns": 0,
  "default": null,
  "depends_on": null,
  "description": null,
  "doctype": "Custom Field",
  "dt": "Lead",
  "fetch_from": null,
  "fetch_if_empty": 0,
  "fieldname": "custom_engagement_type",
  "fieldtype": "Select",
  "hidden": 0,
  "hide_border": 0,
  "hide_days": 0,
  "hide_seconds": 0,
  "ignore_user_permissions": 0,
  "ignore_xss_filter": 0,
  "in_global_search": 0,
  "in_list_view": 0,
  "in_preview": 0,
  "in_standard_filter": 0,
  "insert_after": "custom_estimated_annual_fee",
  "is_system_generated": 0,
  "is_virtual": 0,
  "label": "Engagement Type",
  "length": 0,
  "link_filters": null,
  "mandatory_depends_on": null,
  "module": "Office customisation",
  "name": "Lead-custom_engagement_type",
  "no_copy": 0,
  "non_negative": 0,
  "options": "One-time\nRetainer\nProject-based",
  "permlevel": 0,
  "placeholder": null,
  "precision": "",
  "print_hide": 0,
  "print_hide_if_no_value": 0,
  "print_width": null,
  "read_only": 0,
  "read_only_depends_on": null,
  "report_hide": 0,
  "reqd": 0,
  "search_index": 0,
  "show_dashboard": 0,
  "sort_options": 0,
  "translatable": 0,
  "unique": 0,
  "width": null
 },
 {
  "alignment": "",
  "allow_in_quick_entry": 0,
  "allow_on_submit": 0,
  "bold": 0,
  "button_color": "",
  "collapsible": 0,
  "collapsible_depends_on": null,
  "columns": 0,
  "default": null,
  "depends_on": null,
  "description": null,
  "doctype": "Custom Field",
  "dt": "Lead",
  "fetch_from": null,
  "fetch_if_empty": 0,
  "fieldname": "custom_estimated_annual_fee",
  "fieldtype": "Currency",
  "hidden": 0,
  "hide_border": 0,
  "hide_days": 0,
  "hide_seconds": 0,
  "ignore_user_permissions": 0,
  "ignore_xss_filter": 0,
  "in_global_search": 0,
  "in_list_view": 0,
  "in_preview": 0,
  "in_standard_filter": 0,
  "insert_after": "custom_follow_up_stage",
  "is_system_generated": 0,
  "is_virtual": 0,
  "label": "Estimated Annual Fee",
  "length": 0,
  "link_filters": null,
  "mandatory_depends_on": null,
  "module": "Office customisation",
  "name": "Lead-custom_estimated_annual_fee",
  "no_copy": 0,
  "non_negative": 0,
  "options": null,
  "permlevel": 0,
  "placeholder": null,
  "precision": "",
  "print_hide": 0,
  "print_hide_if_no_value": 0,
  "print_width": null,
  "read_only": 0,
  "read_only_depends_on": null,
  "report_hide": 0,
  "reqd": 0,
  "search_index": 0,
  "show_dashboard": 0,
  "sort_options": 0,
  "translatable": 0,
  "unique": 0,
  "width": null
 },
 {
  "alignment": "",
  "allow_in_quick_entry": 0,
  "allow_on_submit": 0,
  "bold": 0,
  "button_color": "",
  "collapsible": 0,
  "collapsible_depends_on": null,
  "columns": 0,
  "default": null,
  "depends_on": null,
  "description": null,
  "doctype": "Custom Field",
  "dt": "Lead",
  "fetch_from": null,
  "fetch_if_empty": 0,
  "fieldname": "custom_follow_up_date",
  "fieldtype": "Date",
  "hidden": 0,
  "hide_border": 0,
  "hide_days": 0,
  "hide_seconds": 0,
  "ignore_user_permissions": 0,
  "ignore_xss_filter": 0,
  "in_global_search": 0,
  "in_list_view": 0,
  "in_preview": 0,
  "in_standard_filter": 0,
  "insert_after": "custom_service_type",
  "is_system_generated": 0,
  "is_virtual": 0,
  "label": "Follow-up Date",
  "length": 0,
  "link_filters": null,
  "mandatory_depends_on": null,
  "module": "Office customisation",
  "name": "Lead-custom_follow_up_date",
  "no_copy": 0,
  "non_negative": 0,
  "options": null,
  "permlevel": 0,
  "placeholder": null,
  "precision": "",
  "print_hide": 0,
  "print_hide_if_no_value": 0,
  "print_width": null,
  "read_only": 0,
  "read_only_depends_on": null,
  "report_hide": 0,
  "reqd": 0,
  "search_index": 0,
  "show_dashboard": 0,
  "sort_options": 0,
  "translatable": 0,
  "unique": 0,
  "width": null
 },
 {
  "alignment": "",
  "allow_in_quick_entry": 0,
  "allow_on_submit": 0,
  "bold": 0,
  "button_color": "",
  "collapsible": 0,
  "collapsible_depends_on": null,
  "columns": 0,
  "default": null,
  "depends_on": null,
  "description": null,
  "doctype": "Custom Field",
  "dt": "Lead",
  "fetch_from": null,
  "fetch_if_empty": 0,
  "fieldname": "custom_follow_up_stage",
  "fieldtype": "Select",
  "hidden": 0,
  "hide_border": 0,
  "hide_days": 0,
  "hide_seconds": 0,
  "ignore_user_permissions": 0,
  "ignore_xss_filter": 0,
  "in_global_search": 0,
  "in_list_view": 0,
  "in_preview": 0,
  "in_standard_filter": 0,
  "insert_after": "custom_follow_up_date",
  "is_system_generated": 0,
  "is_virtual": 0,
  "label": "Follow-up Stage",
  "length": 0,
  "link_filters": null,
  "mandatory_depends_on": null,
  "module": "Office customisation",
  "name": "Lead-custom_follow_up_stage",
  "no_copy": 0,
  "non_negative": 0,
  "options": "Initial Contact\nDiscovery Call Scheduled\nProposal Sent\nNegotiation\nAwaiting Decision\nWon\nLost\nOn Hold",
  "permlevel": 0,
  "placeholder": null,
  "precision": "",
  "print_hide": 0,
  "print_hide_if_no_value": 0,
  "print_width": null,
  "read_only": 0,
  "read_only_depends_on": null,
  "report_hide": 0,
  "reqd": 0,
  "search_index": 0,
  "show_dashboard": 0,
  "sort_options": 0,
  "translatable": 0,
  "unique": 0,
  "width": null
 },
 {
  "alignment": "",
  "allow_in_quick_entry": 0,
  "allow_on_submit": 0,
  "bold": 0,
  "button_color": "",
  "collapsible": 0,
  "collapsible_depends_on": null,
  "columns": 0,
  "default": null,
  "depends_on": null,
  "description": null,
  "doctype": "Custom Field",
  "dt": "Lead",
  "fetch_from": null,
  "fetch_if_empty": 0,
  "fieldname": "custom_lead_source",
  "fieldtype": "Select",
  "hidden": 0,
  "hide_border": 0,
  "hide_days": 0,
  "hide_seconds": 0,
  "ignore_user_permissions": 0,
  "ignore_xss_filter": 0,
  "in_global_search": 0,
  "in_list_view": 0,
  "in_preview": 0,
  "in_standard_filter": 0,
  "insert_after": "custom_referred_by",
  "is_system_generated": 0,
  "is_virtual": 0,
  "label": "Lead Source",
  "length": 0,
  "link_filters": null,
  "mandatory_depends_on": null,
  "module": "Office customisation",
  "name": "Lead-custom_lead_source",
  "no_copy": 0,
  "non_negative": 0,
  "options": "Referral\nDirect Call\nTelegram\nWhatsApp\nWebsite\nLinkedIn\nCA Network\nEvent / Seminar\nExisting Client Upsell\nWalk-in",
  "permlevel": 0,
  "placeholder": null,
  "precision": "",
  "print_hide": 0,
  "print_hide_if_no_value": 0,
  "print_width": null,
  "read_only": 0,
  "read_only_depends_on": null,
  "report_hide": 0,
  "reqd": 0,
  "search_index": 0,
  "show_dashboard": 0,
  "sort_options": 0,
  "translatable": 0,
  "unique": 0,
  "width": null
 },
 {
  "alignment": "",
  "allow_in_quick_entry": 0,
  "allow_on_submit": 0,
  "bold": 0,
  "button_color": "",
  "collapsible": 0,
  "collapsible_depends_on": null,
  "columns": 0,
  "default": null,
  "depends_on": null,
  "description": null,
  "doctype": "Custom Field",
  "dt": "Lead",
  "fetch_from": null,
  "fetch_if_empty": 0,
  "fieldname": "custom_lead_temperature",
  "fieldtype": "Select",
  "hidden": 0,
  "hide_border": 0,
  "hide_days": 0,
  "hide_seconds": 0,
  "ignore_user_permissions": 0,
  "ignore_xss_filter": 0,
  "in_global_search": 0,
  "in_list_view": 0,
  "in_preview": 0,
  "in_standard_filter": 0,
  "insert_after": "status",
  "is_system_generated": 0,
  "is_virtual": 0,
  "label": "Lead Temperature",
  "length": 0,
  "link_filters": null,
  "mandatory_depends_on": null,
  "module": "Office customisation",
  "name": "Lead-custom_lead_temperature",
  "no_copy": 0,
  "non_negative": 0,
  "options": "Hot\nWarm\nCold",
  "permlevel": 0,
  "placeholder": null,
  "precision": "",
  "print_hide": 0,
  "print_hide_if_no_value": 0,
  "print_width": null,
  "read_only": 0,
  "read_only_depends_on": null,
  "report_hide": 0,
  "reqd": 0,
  "search_index": 0,
  "show_dashboard": 0,
  "sort_options": 0,
  "translatable": 0,
  "unique": 0,
  "width": null
 },
 {
  "alignment": "",
  "allow_in_quick_entry": 0,
  "allow_on_submit": 0,
  "bold": 0,
  "button_color": "",
  "collapsible": 0,
  "collapsible_depends_on": null,
  "columns": 0,
  "default": null,
  "depends_on": null,
  "description": null,
  "doctype": "Custom Field",
  "dt": "Lead",
  "fetch_from": null,
  "fetch_if_empty": 0,
  "fieldname": "custom_referred_by",
  "fieldtype": "Data",
  "hidden": 0,
  "hide_border": 0,
  "hide_days": 0,
  "hide_seconds": 0,
  "ignore_user_permissions": 0,
  "ignore_xss_filter": 0,
  "in_global_search": 0,
  "in_list_view": 0,
  "in_preview": 0,
  "in_standard_filter": 0,
  "insert_after": "source",
  "is_system_generated": 0,
  "is_virtual": 0,
  "label": "Referred By",
  "length": 0,
  "link_filters": null,
  "mandatory_depends_on": null,
  "module": "Office customisation",
  "name": "Lead-custom_referred_by",
  "no_copy": 0,
  "non_negative": 0,
  "options": null,
  "permlevel": 0,
  "placeholder": null,
  "precision": "",
  "print_hide": 0,
  "print_hide_if_no_value": 0,
  "print_width": null,
  "read_only": 0,
  "read_only_depends_on": null,
  "report_hide": 0,
  "reqd": 0,
  "search_index": 0,
  "show_dashboard": 0,
  "sort_options": 0,
  "translatable": 0,
  "unique": 0,
  "width": null
 },
 {
  "alignment": "",
  "allow_in_quick_entry": 0,
  "allow_on_submit": 0,
  "bold": 0,
  "button_color": "",
  "collapsible": 0,
  "collapsible_depends_on": null,
  "columns": 0,
  "default": null,
  "depends_on": null,
  "description": null,
  "doctype": "Custom Field",
  "dt": "Lead",
  "fetch_from": null,
  "fetch_if_empty": 0,
  "fieldname": "custom_service_type",
  "fieldtype": "Select",
  "hidden": 0,
  "hide_border": 0,
  "hide_days": 0,
  "hide_seconds": 0,
  "ignore_user_permissions": 0,
  "ignore_xss_filter": 0,
  "in_global_search": 0,
  "in_list_view": 0,
  "in_preview": 0,
  "in_standard_filter": 0,
  "insert_after": "qualification_status",
  "is_system_generated": 0,
  "is_virtual": 0,
  "label": "Service Type",
  "length": 0,
  "link_filters": null,
  "mandatory_depends_on": null,
  "module": "Office customisation",
  "name": "Lead-custom_service_type",
  "no_copy": 0,
  "non_negative": 0,
  "options": "GST Compliance\nIncome Tax\nTax Audit\nInternal Audit\nCompany Law / ROC\nFEMA Advisory\nStartup CFO Advisory\nESOP Advisory\nFundraise Support\nBusiness Consulting\nBookkeeping\nTransaction Advisory\nLitigation Support\nOther",
  "permlevel": 0,
  "placeholder": null,
  "precision": "",
  "print_hide": 0,
  "print_hide_if_no_value": 0,
  "print_width": null,
  "read_only": 0,
  "read_only_depends_on": null,
  "report_hide": 0,
  "reqd": 0,
  "search_index": 0,
  "show_dashboard": 0,
  "sort_options": 0,
  "translatable": 0,
  "unique": 0,
  "width": null
 },
 {
  "alignment": "",
  "allow_in_quick_entry": 0,
  "allow_on_submit": 0,
  "bold": 0,
  "button_color": "",
  "collapsible": 0,
  "collapsible_depends_on": null,
  "columns": 0,
  "default": "M",
  "depends_on": null,
  "description": null,
  "doctype": "Custom Field",
  "dt": "Task",
  "fetch_from": null,
  "fetch_if_empty": 0,
  "fieldname": "custom_estimated_effort",
  "fieldtype": "Select",
  "hidden": 0,
  "hide_border": 0,
  "hide_days": 0,
  "hide_seconds": 0,
  "ignore_user_permissions": 0,
  "ignore_xss_filter": 0,
  "in_global_search": 0,
  "in_list_view": 1,
  "in_preview": 0,
  "in_standard_filter": 1,
  "insert_after": "priority",
  "is_system_generated": 0,
  "is_virtual": 0,
  "label": "Effort",
  "length": 0,
  "link_filters": null,
  "mandatory_depends_on": null,
  "module": "Office customisation",
  "name": "Task-custom_estimated_effort",
  "no_copy": 0,
  "non_negative": 0,
  "options": "\nS\nM\nL\nXL",
  "permlevel": 0,
  "placeholder": null,
  "precision": "",
  "print_hide": 0,
  "print_hide_if_no_value": 0,
  "print_width": null,
  "read_only": 0,
  "read_only_depends_on": null,
  "report_hide": 0,
  "reqd": 0,
  "search_index": 0,
  "show_dashboard": 0,
  "sort_options": 0,
  "translatable": 0,
  "unique": 0,
  "width": null
 },
 {
  "alignment": "",
  "allow_in_quick_entry": 0,
  "allow_on_submit": 0,
  "bold": 0,
  "button_color": "",
  "collapsible": 0,
  "collapsible_depends_on": null,
  "columns": 0,
  "default": null,
  "depends_on": null,
  "description": null,
  "doctype": "Custom Field",
  "dt": "Task",
  "fetch_from": null,
  "fetch_if_empty": 0,
  "fieldname": "custom_task_list",
  "fieldtype": "Link",
  "hidden": 0,
  "hide_border": 0,
  "hide_days": 0,
  "hide_seconds": 0,
  "ignore_user_permissions": 0,
  "ignore_xss_filter": 0,
  "in_global_search": 0,
  "in_list_view": 0,
  "in_preview": 0,
  "in_standard_filter": 0,
  "insert_after": "section_break_dafi",
  "is_system_generated": 0,
  "is_virtual": 0,
  "label": "Task List",
  "length": 0,
  "link_filters": null,
  "mandatory_depends_on": null,
  "module": "Office customisation",
  "name": "Task-custom_task_list",
  "no_copy": 0,
  "non_negative": 0,
  "options": "Task List",
  "permlevel": 0,
  "placeholder": null,
  "precision": "",
  "print_hide": 0,
  "print_hide_if_no_value": 0,
  "print_width": null,
  "read_only": 0,
  "read_only_depends_on": null,
  "report_hide": 0,
  "reqd": 0,
  "search_index": 0,
  "show_dashboard": 0,
  "sort_options": 0,
  "translatable": 0,
  "unique": 0,
  "width": null
 },
 {
  "alignment": null,
  "allow_in_quick_entry": 0,
  "allow_on_submit": 1,
  "bold": 0,
  "button_color": null,
  "collapsible": 0,
  "collapsible_depends_on": null,
  "columns": 0,
  "default": null,
  "depends_on": null,
  "description": null,
  "doctype": "Custom Field",
  "dt": "Work Order",
  "fetch_from": null,
  "fetch_if_empty": 0,
  "fieldname": "custom_team_assignment_tab",
  "fieldtype": "Tab Break",
  "hidden": 0,
  "hide_border": 0,
  "hide_days": 0,
  "hide_seconds": 0,
  "ignore_user_permissions": 0,
  "ignore_xss_filter": 0,
  "in_global_search": 0,
  "in_list_view": 0,
  "in_preview": 0,
  "in_standard_filter": 0,
  "insert_after": "amended_from",
  "is_system_generated": 0,
  "is_virtual": 0,
  "label": "Team Assignment",
  "length": 0,
  "link_filters": null,
  "mandatory_depends_on": null,
  "module": "Office customisation",
  "name": "Work Order-custom_team_assignment_tab",
  "no_copy": 0,
  "non_negative": 0,
  "options": null,
  "permlevel": 0,
  "placeholder": null,
  "precision": null,
  "print_hide": 0,
  "print_hide_if_no_value": 0,
  "print_width": null,
  "read_only": 0,
  "read_only_depends_on": null,
  "report_hide": 0,
  "reqd": 0,
  "search_index": 0,
  "show_dashboard": 0,
  "sort_options": 0,
  "translatable": 0,
  "unique": 0,
  "width": null
 },
 {
  "alignment": null,
  "allow_in_quick_entry": 0,
  "allow_on_submit": 1,
  "bold": 0,
  "button_color": null,
  "collapsible": 0,
  "collapsible_depends_on": null,
  "columns": 0,
  "default": null,
  "depends_on": null,
  "description": null,
  "doctype": "Custom Field",
  "dt": "Work Order",
  "fetch_from": null,
  "fetch_if_empty": 0,
  "fieldname": "custom_team_members",
  "fieldtype": "Table",
  "hidden": 0,
  "hide_border": 0,
  "hide_days": 0,
  "hide_seconds": 0,
  "ignore_user_permissions": 0,
  "ignore_xss_filter": 0,
  "in_global_search": 0,
  "in_list_view": 0,
  "in_preview": 0,
  "in_standard_filter": 0,
  "insert_after": "custom_team_assignment_tab",
  "is_system_generated": 0,
  "is_virtual": 0,
  "label": "Team Members",
  "length": 0,
  "link_filters": null,
  "mandatory_depends_on": null,
  "module": "Office customisation",
  "name": "Work Order-custom_team_members",
  "no_copy": 0,
  "non_negative": 0,
  "options": "Work Order Team Member",
  "permlevel": 0,
  "placeholder": null,
  "precision": null,
  "print_hide": 0,
  "print_hide_if_no_value": 0,
  "print_width": null,
  "read_only": 0,
  "read_only_depends_on": null,
  "report_hide": 0,
  "reqd": 0,
  "search_index": 0,
  "show_dashboard": 0,
  "sort_options": 0,
  "translatable": 0,
  "unique": 0,
  "width": null
 }
]
